fastmobo-0.1.8.dist-info/METADATA
fastmobo-0.1.8.dist-info/WHEEL
fastmobo-0.1.8.dist-info/entry_points.txt
fastmobo/__init__.py
fastmobo/fit.py
fastmobo/mobo.py
fastmobo/problems.py
fastmobo-0.1.8.dist-info/RECORD
