Metadata-Version: 2.1
Name: fastmobo
Version: 0.1.8
Summary: Multi-objective Bayesian optimization Framework (Botorch Wrapper)
Author-Email: abdelrahman abounida <abdelrahmanaboneda@gmail.com>
License: MIT
Requires-Python: <3.13,>=3.11
Requires-Dist: botorch>=0.15.0
Requires-Dist: loguru>=0.7.3
Requires-Dist: matplotlib>=3.10.6
